rdbtools3-0.1.2.dist-info/DESCRIPTION.rst
rdbtools3-0.1.2.dist-info/top_level.txt
rdbtools3-0.1.2.dist-info/METADATA
rdbtools3-0.1.2.dist-info/RECORD
rdbtools3-0.1.2.dist-info/metadata.json
rdbtools3-0.1.2.dist-info/WHEEL
rdbtools3/parser.py
rdbtools3/intset.py
rdbtools3/__init__.py
rdbtools3/ziplist.py
rdbtools3/exceptions.py
rdbtools3/util.py
rdbtools3/consts.py
rdbtools3/lzf.py
rdbtools3/zipmap.py
rdbtools3/cli/__main__.py
rdbtools3/cli/__init__.py
